craftscript/__init__.py
craftscript/blocks.py
craftscript/datapack.py
craftscript/items.py
craftscript/recipes.py
craftscript/utils.py
craftscript/kubejs/__init__.py
craftscript/kubejs/blocks.py
craftscript/kubejs/generator.py
craftscript/kubejs/items.py
craftscript/kubejs/recipes.py
craftscript/templates/advancement.json
craftscript/templates/block_state.json
craftscript/templates/item_model.json
craftscript-1.0.8.dist-info/METADATA
craftscript-1.0.8.dist-info/WHEEL
craftscript-1.0.8.dist-info/top_level.txt
craftscript-1.0.8.dist-info/RECORD
